anystore/__init__.py
anystore/cli.py
anystore/decorators.py
anystore/exceptions.py
anystore/functools.py
anystore/io.py
anystore/lock.py
anystore/logging.py
anystore/mirror.py
anystore/mixins.py
anystore/model.py
anystore/py.typed
anystore/queue.py
anystore/serialize.py
anystore/settings.py
anystore/store/__init__.py
anystore/store/abstract.py
anystore/store/base.py
anystore/store/fs.py
anystore/store/memory.py
anystore/store/redis.py
anystore/store/sql.py
anystore/store/virtual.py
anystore/store/zip.py
anystore/tags.py
anystore/types.py
anystore/util.py
anystore-0.4.3.dist-info/METADATA
anystore-0.4.3.dist-info/WHEEL
anystore-0.4.3.dist-info/entry_points.txt
anystore-0.4.3.dist-info/licenses/LICENSE
anystore-0.4.3.dist-info/licenses/NOTICE
anystore-0.4.3.dist-info/RECORD
