Metadata-Version: 2.4
Name: anystore
Version: 0.4.3
Summary: Store and cache things anywhere
License: AGPLv3+
License-File: LICENSE
License-File: NOTICE
Author: Simon Wörpel
Author-email: simon.woerpel@pm.me
Requires-Python: >=3.11,<4
Classifier: Intended Audience :: Developers
Classifier: Operating System :: OS Independent
Classifier: Programming Language :: Python
Classifier: Programming Language :: Python :: 3.11
Classifier: Programming Language :: Python :: 3.12
Classifier: Programming Language :: Python :: 3.13
Classifier: Programming Language :: Python :: 3.14
Provides-Extra: redis
Provides-Extra: sql
Requires-Dist: banal (>=1.0.6,<2.0.0)
Requires-Dist: cloudpickle (>=3.1.0,<4.0.0)
Requires-Dist: dateparser (>=1.2.2,<2.0.0)
Requires-Dist: fakeredis (>=2.26.2,<3.0.0) ; extra == "redis"
Requires-Dist: fsspec (>2023.10,<2026)
Requires-Dist: httpx (>=0.28.1,<0.29.0)
Requires-Dist: orjson (>=3.10.18,<4.0.0)
Requires-Dist: pyaml (>=25.5.0,<26.0.0)
Requires-Dist: pydantic (>=2.11.7,<3.0.0)
Requires-Dist: pydantic-settings (>=2.7.1,<3.0.0)
Requires-Dist: redis (>=4.0.0) ; extra == "redis"
Requires-Dist: rich (>=10.0.0,<15.0.0)
Requires-Dist: rigour (>=1.0.0,<2.0.0)
Requires-Dist: s3fs (>2023.10,<2026)
Requires-Dist: sqlalchemy (>=2.0.36,<3.0.0) ; extra == "sql"
Requires-Dist: structlog (>=22.0.0,<26.0.0)
Requires-Dist: tqdm (>=4.67.1,<5.0.0)
Requires-Dist: typer (>=0.17)
Requires-Dist: uuid7 (>=0.1.0,<0.2.0)
Project-URL: Documentation, https://docs.investigraph.dev/lib/anystore
Project-URL: Homepage, https://docs.investigraph.dev/lib/anystore
Project-URL: Issues, https://github.com/dataresearchcenter/anystore/issues
Project-URL: Repository, https://github.com/dataresearchcenter/anystore
